primePy/__init__.py
primePy/primePy.py
primePy-1.1.dist-info/METADATA
primePy-1.1.dist-info/RECORD
primePy-1.1.dist-info/WHEEL
primePy-1.1.dist-info/top_level.txt
