Metadata-Version: 2.1
Name: primePy
Version: 1.1
Summary: This module contains several useful functions to work with prime numbers. For example, extracting all the prime factors (with multiplicity) of a positive integer reasonably fast.
Home-page: https://github.com/janaindrajit/primes
Author: Indrajit Jana
Author-email: ijana@temple.edu
License: UNKNOWN
Keywords: fast,prime,facorization
Platform: UNKNOWN
Classifier: Programming Language :: Python :: 3
Classifier: License :: OSI Approved :: MIT License
Classifier: Operating System :: OS Independent
